apply_pandas/__init__.py
apply_pandas/apply.py
apply_pandas-0.0.1.dist-info/LICENSE
apply_pandas-0.0.1.dist-info/METADATA
apply_pandas-0.0.1.dist-info/WHEEL
apply_pandas-0.0.1.dist-info/top_level.txt
apply_pandas-0.0.1.dist-info/RECORD
