Metadata-Version: 2.1
Name: apply-pandas
Version: 0.0.1
Summary: Functor to convert string boolean expressions into Pandas DataFrame filters.
Home-page: https://github.com/PrasannaMaddila/apply-pandas
Author: sharknaedo (Prasanna Maddila)
Author-email: maddilaprasanna10@gmail.com
License: UNKNOWN
Project-URL: Bug Tracker, https://github.com/PrasannaMaddila/apply-pandas/issues
Platform: UNKNOWN
Classifier: Programming Language :: Python :: 3
Classifier: License :: OSI Approved :: GNU General Public License v3 or later (GPLv3+)
Classifier: Operating System :: OS Independent
Requires-Python: >=3.6
License-File: LICENSE
